qcrop/__init__.py
qcrop/__main__.py
qcrop/area_selector.py
qcrop/assets_rc.py
qcrop/qcrop_ui.py
qcrop/ui.py
qcrop-0.0.1.dist-info/LICENSE.txt
qcrop-0.0.1.dist-info/METADATA
qcrop-0.0.1.dist-info/WHEEL
qcrop-0.0.1.dist-info/entry_points.txt
qcrop-0.0.1.dist-info/top_level.txt
qcrop-0.0.1.dist-info/RECORD
